mara_superset/__init__.py
mara_superset/cli.py
mara_superset/client.py
mara_superset/config.py
mara_superset/metadata.py
mara_superset/views.py
mara_superset/.scripts/README.md
mara_superset/.scripts/superset.mk
mara_superset-1.0.4.dist-info/LICENSE
mara_superset-1.0.4.dist-info/METADATA
mara_superset-1.0.4.dist-info/WHEEL
mara_superset-1.0.4.dist-info/top_level.txt
mara_superset-1.0.4.dist-info/RECORD
