Metadata-Version: 2.1
Name: mara-superset
Version: 1.0.4
Summary: Configuring Apache Superset from a Mara Schema
Home-page: https://github.com/mara/mara-superset
Author: Mara contributors
License: MIT
Requires-Python: >=3.6
License-File: LICENSE
Requires-Dist: mara-db (>=4.7.1)
Requires-Dist: mara-page (>=1.3.0)
Requires-Dist: mara-schema (>=1.0.0)
Requires-Dist: click
Requires-Dist: requests
Provides-Extra: dev
Requires-Dist: apache-superset (>=1.3.2) ; extra == 'dev'
